{
    "info": {
        "title": "default-title",
        "version": "1.0.0"
    },
    "paths": {
        "/does/exist": {
            "get": {
                "responses": {
                    "200": {
                        "description": "default-response",
                        "headers": {
                            "x-value": {
                                "maxLength": 3,
                                "type": "string"
                            }
                        }
                    }
                }
            }
        }
    },
    "swagger": "2.0"
}